<?xml version="1.0" standalone="yes"?>
<NewDataSet>
  <xs:schema id="NewDataSet" xmlns="" xmlns:xs="http://www.w3.org/2001/XMLSchema" xmlns:msdata="urn:schemas-microsoft-com:xml-msdata">
    <xs:element name="NewDataSet" msdata:IsDataSet="true" msdata:UseCurrentLocale="true">
      <xs:complexType>
        <xs:choice minOccurs="0" maxOccurs="unbounded">
          <xs:element name="Prezzi">
            <xs:complexType>
              <xs:sequence>
                <xs:element name="Data" type="xs:string" minOccurs="0" />
                <xs:element name="Mercato" type="xs:string" minOccurs="0" />
                <xs:element name="Ora" type="xs:string" minOccurs="0" />
                <xs:element name="PUN" type="xs:string" minOccurs="0" />
                <xs:element name="NAT" type="xs:string" minOccurs="0" />
                <xs:element name="CNOR" type="xs:string" minOccurs="0" />
                <xs:element name="CSUD" type="xs:string" minOccurs="0" />
                <xs:element name="NORD" type="xs:string" minOccurs="0" />
                <xs:element name="SARD" type="xs:string" minOccurs="0" />
                <xs:element name="SICI" type="xs:string" minOccurs="0" />
                <xs:element name="SUD" type="xs:string" minOccurs="0" />
                <xs:element name="AUST" type="xs:string" minOccurs="0" />
                <xs:element name="BRNN" type="xs:string" minOccurs="0" />
                <xs:element name="COAC" type="xs:string" minOccurs="0" />
                <xs:element name="CORS" type="xs:string" minOccurs="0" />
                <xs:element name="FOGN" type="xs:string" minOccurs="0" />
                <xs:element name="FRAN" type="xs:string" minOccurs="0" />
                <xs:element name="GREC" type="xs:string" minOccurs="0" />
                <xs:element name="MFTV" type="xs:string" minOccurs="0" />
                <xs:element name="PRGP" type="xs:string" minOccurs="0" />
                <xs:element name="ROSN" type="xs:string" minOccurs="0" />
                <xs:element name="SLOV" type="xs:string" minOccurs="0" />
                <xs:element name="SVIZ" type="xs:string" minOccurs="0" />
                <xs:element name="BSP" type="xs:string" minOccurs="0" />
                <xs:element name="MALT" type="xs:string" minOccurs="0" />
                <xs:element name="XAUS" type="xs:string" minOccurs="0" />
                <xs:element name="XFRA" type="xs:string" minOccurs="0" />
              </xs:sequence>
            </xs:complexType>
          </xs:element>
        </xs:choice>
      </xs:complexType>
    </xs:element>
  </xs:schema>
  <Prezzi>
    <Data>20170107</Data>
    <Mercato>MGP</Mercato>
    <Ora>1</Ora>
    <PUN>50,531810</PUN>
    <NAT>52,000000</NAT>
    <CNOR>49,700000</CNOR>
    <CSUD>47,000000</CSUD>
    <NORD>53,260000</NORD>
    <SARD>47,000000</SARD>
    <SICI>47,000000</SICI>
    <SUD>47,000000</SUD>
    <AUST>53,260000</AUST>
    <BRNN>47,000000</BRNN>
    <COAC>47,000000</COAC>
    <CORS>49,700000</CORS>
    <FOGN>47,000000</FOGN>
    <FRAN>53,260000</FRAN>
    <GREC>47,000000</GREC>
    <MFTV>53,260000</MFTV>
    <PRGP>47,000000</PRGP>
    <ROSN>47,000000</ROSN>
    <SLOV>53,260000</SLOV>
    <SVIZ>53,260000</SVIZ>
    <BSP>53,260000</BSP>
    <MALT>47,000000</MALT>
    <XAUS>53,260000</XAUS>
    <XFRA>53,260000</XFRA>
  </Prezzi>
  <Prezzi>
    <Data>20170107</Data>
    <Mercato>MGP</Mercato>
    <Ora>2</Ora>
    <PUN>47,643170</PUN>
    <NAT>48,100000</NAT>
    <CNOR>49,700000</CNOR>
    <CSUD>40,650000</CSUD>
    <NORD>52,050000</NORD>
    <SARD>40,650000</SARD>
    <SICI>40,650000</SICI>
    <SUD>40,650000</SUD>
    <AUST>52,050000</AUST>
    <BRNN>40,650000</BRNN>
    <COAC>40,650000</COAC>
    <CORS>49,700000</CORS>
    <FOGN>40,650000</FOGN>
    <FRAN>52,050000</FRAN>
    <GREC>40,650000</GREC>
    <MFTV>52,050000</MFTV>
    <PRGP>40,650000</PRGP>
    <ROSN>40,650000</ROSN>
    <SLOV>52,050000</SLOV>
    <SVIZ>52,050000</SVIZ>
    <BSP>52,050000</BSP>
    <MALT>40,650000</MALT>
    <XAUS>52,050000</XAUS>
    <XFRA>52,050000</XFRA>
  </Prezzi>
  <Prezzi>
    <Data>20170107</Data>
    <Mercato>MGP</Mercato>
    <Ora>3</Ora>
    <PUN>47,129400</PUN>
    <NAT>47,640000</NAT>
    <CNOR>49,700000</CNOR>
    <CSUD>40,650000</CSUD>
    <NORD>51,050000</NORD>
    <SARD>40,650000</SARD>
    <SICI>40,650000</SICI>
    <SUD>40,650000</SUD>
    <AUST>51,050000</AUST>
    <BRNN>40,650000</BRNN>
    <COAC>40,650000</COAC>
    <CORS>49,700000</CORS>
    <FOGN>40,650000</FOGN>
    <FRAN>51,050000</FRAN>
    <GREC>40,650000</GREC>
    <MFTV>51,050000</MFTV>
    <PRGP>40,650000</PRGP>
    <ROSN>40,650000</ROSN>
    <SLOV>51,050000</SLOV>
    <SVIZ>51,050000</SVIZ>
    <BSP>51,050000</BSP>
    <MALT>40,650000</MALT>
    <XAUS>51,050000</XAUS>
    <XFRA>51,050000</XFRA>
  </Prezzi>
  <Prezzi>
    <Data>20170107</Data>
    <Mercato>MGP</Mercato>
    <Ora>4</Ora>
    <PUN>47,661370</PUN>
    <NAT>45,490000</NAT>
    <CNOR>49,700000</CNOR>
    <CSUD>40,640000</CSUD>
    <NORD>52,000000</NORD>
    <SARD>40,640000</SARD>
    <SICI>40,640000</SICI>
    <SUD>40,640000</SUD>
    <AUST>52,000000</AUST>
    <BRNN>40,640000</BRNN>
    <COAC>40,640000</COAC>
    <CORS>49,700000</CORS>
    <FOGN>40,640000</FOGN>
    <FRAN>52,000000</FRAN>
    <GREC>40,640000</GREC>
    <MFTV>52,000000</MFTV>
    <PRGP>40,640000</PRGP>
    <ROSN>40,640000</ROSN>
    <SLOV>52,000000</SLOV>
    <SVIZ>52,000000</SVIZ>
    <BSP>52,000000</BSP>
    <MALT>40,640000</MALT>
    <XAUS>52,000000</XAUS>
    <XFRA>52,000000</XFRA>
  </Prezzi>
  <Prezzi>
    <Data>20170107</Data>
    <Mercato>MGP</Mercato>
    <Ora>5</Ora>
    <PUN>45,539540</PUN>
    <NAT>45,490000</NAT>
    <CNOR>49,700000</CNOR>
    <CSUD>36,440000</CSUD>
    <NORD>50,780000</NORD>
    <SARD>36,440000</SARD>
    <SICI>36,440000</SICI>
    <SUD>36,440000</SUD>
    <AUST>50,780000</AUST>
    <BRNN>36,440000</BRNN>
    <COAC>36,440000</COAC>
    <CORS>49,700000</CORS>
    <FOGN>36,440000</FOGN>
    <FRAN>50,780000</FRAN>
    <GREC>36,440000</GREC>
    <MFTV>50,780000</MFTV>
    <PRGP>36,440000</PRGP>
    <ROSN>36,440000</ROSN>
    <SLOV>50,780000</SLOV>
    <SVIZ>50,780000</SVIZ>
    <BSP>50,780000</BSP>
    <MALT>36,440000</MALT>
    <XAUS>50,780000</XAUS>
    <XFRA>50,780000</XFRA>
  </Prezzi>
  <Prezzi>
    <Data>20170107</Data>
    <Mercato>MGP</Mercato>
    <Ora>6</Ora>
    <PUN>47,009890</PUN>
    <NAT>45,740000</NAT>
    <CNOR>49,700000</CNOR>
    <CSUD>40,650000</CSUD>
    <NORD>50,738700</NORD>
    <SARD>40,650000</SARD>
    <SICI>40,650000</SICI>
    <SUD>40,650000</SUD>
    <AUST>50,738700</AUST>
    <BRNN>40,650000</BRNN>
    <COAC>40,650000</COAC>
    <CORS>49,700000</CORS>
    <FOGN>40,650000</FOGN>
    <FRAN>50,738700</FRAN>
    <GREC>40,650000</GREC>
    <MFTV>50,738700</MFTV>
    <PRGP>40,650000</PRGP>
    <ROSN>40,650000</ROSN>
    <SLOV>50,738700</SLOV>
    <SVIZ>50,738700</SVIZ>
    <BSP>50,738700</BSP>
    <MALT>40,650000</MALT>
    <XAUS>50,738700</XAUS>
    <XFRA>50,738700</XFRA>
  </Prezzi>
  <Prezzi>
    <Data>20170107</Data>
    <Mercato>MGP</Mercato>
    <Ora>7</Ora>
    <PUN>48,949770</PUN>
    <NAT>49,700000</NAT>
    <CNOR>49,700000</CNOR>
    <CSUD>41,000000</CSUD>
    <NORD>54,080000</NORD>
    <SARD>41,000000</SARD>
    <SICI>41,000000</SICI>
    <SUD>41,000000</SUD>
    <AUST>54,080000</AUST>
    <BRNN>41,000000</BRNN>
    <COAC>41,000000</COAC>
    <CORS>49,700000</CORS>
    <FOGN>41,000000</FOGN>
    <FRAN>54,080000</FRAN>
    <GREC>41,000000</GREC>
    <MFTV>54,080000</MFTV>
    <PRGP>41,000000</PRGP>
    <ROSN>41,000000</ROSN>
    <SLOV>54,080000</SLOV>
    <SVIZ>54,080000</SVIZ>
    <BSP>54,080000</BSP>
    <MALT>41,000000</MALT>
    <XAUS>54,080000</XAUS>
    <XFRA>54,080000</XFRA>
  </Prezzi>
  <Prezzi>
    <Data>20170107</Data>
    <Mercato>MGP</Mercato>
    <Ora>8</Ora>
    <PUN>55,099110</PUN>
    <NAT>53,000000</NAT>
    <CNOR>56,280000</CNOR>
    <CSUD>53,000000</CSUD>
    <NORD>56,280000</NORD>
    <SARD>53,000000</SARD>
    <SICI>53,000000</SICI>
    <SUD>53,000000</SUD>
    <AUST>56,280000</AUST>
    <BRNN>53,000000</BRNN>
    <COAC>53,000000</COAC>
    <CORS>56,280000</CORS>
    <FOGN>53,000000</FOGN>
    <FRAN>56,280000</FRAN>
    <GREC>53,000000</GREC>
    <MFTV>56,280000</MFTV>
    <PRGP>53,000000</PRGP>
    <ROSN>53,000000</ROSN>
    <SLOV>56,280000</SLOV>
    <SVIZ>56,280000</SVIZ>
    <BSP>56,280000</BSP>
    <MALT>53,000000</MALT>
    <XAUS>56,280000</XAUS>
    <XFRA>56,280000</XFRA>
  </Prezzi>
  <Prezzi>
    <Data>20170107</Data>
    <Mercato>MGP</Mercato>
    <Ora>9</Ora>
    <PUN>57,518140</PUN>
    <NAT>55,000000</NAT>
    <CNOR>53,360000</CNOR>
    <CSUD>53,360000</CSUD>
    <NORD>61,280000</NORD>
    <SARD>53,360000</SARD>
    <SICI>53,360000</SICI>
    <SUD>53,360000</SUD>
    <AUST>61,280000</AUST>
    <BRNN>53,360000</BRNN>
    <COAC>53,360000</COAC>
    <CORS>53,360000</CORS>
    <FOGN>53,360000</FOGN>
    <FRAN>61,280000</FRAN>
    <GREC>53,360000</GREC>
    <MFTV>61,280000</MFTV>
    <PRGP>53,360000</PRGP>
    <ROSN>53,360000</ROSN>
    <SLOV>61,280000</SLOV>
    <SVIZ>61,280000</SVIZ>
    <BSP>61,280000</BSP>
    <MALT>53,360000</MALT>
    <XAUS>61,280000</XAUS>
    <XFRA>61,280000</XFRA>
  </Prezzi>
  <Prezzi>
    <Data>20170107</Data>
    <Mercato>MGP</Mercato>
    <Ora>10</Ora>
    <PUN>60,998820</PUN>
    <NAT>59,400000</NAT>
    <CNOR>65,700000</CNOR>
    <CSUD>53,000000</CSUD>
    <NORD>65,700000</NORD>
    <SARD>53,000000</SARD>
    <SICI>53,000000</SICI>
    <SUD>53,000000</SUD>
    <AUST>65,700000</AUST>
    <BRNN>53,000000</BRNN>
    <COAC>53,000000</COAC>
    <CORS>65,700000</CORS>
    <FOGN>53,000000</FOGN>
    <FRAN>65,700000</FRAN>
    <GREC>53,000000</GREC>
    <MFTV>65,700000</MFTV>
    <PRGP>53,000000</PRGP>
    <ROSN>53,000000</ROSN>
    <SLOV>65,700000</SLOV>
    <SVIZ>65,700000</SVIZ>
    <BSP>65,700000</BSP>
    <MALT>53,000000</MALT>
    <XAUS>65,700000</XAUS>
    <XFRA>65,700000</XFRA>
  </Prezzi>
  <Prezzi>
    <Data>20170107</Data>
    <Mercato>MGP</Mercato>
    <Ora>11</Ora>
    <PUN>59,002460</PUN>
    <NAT>54,000000</NAT>
    <CNOR>63,100000</CNOR>
    <CSUD>52,000000</CSUD>
    <NORD>63,100000</NORD>
    <SARD>52,000000</SARD>
    <SICI>52,000000</SICI>
    <SUD>52,000000</SUD>
    <AUST>63,100000</AUST>
    <BRNN>52,000000</BRNN>
    <COAC>52,000000</COAC>
    <CORS>63,100000</CORS>
    <FOGN>52,000000</FOGN>
    <FRAN>63,100000</FRAN>
    <GREC>52,000000</GREC>
    <MFTV>63,100000</MFTV>
    <PRGP>52,000000</PRGP>
    <ROSN>52,000000</ROSN>
    <SLOV>63,100000</SLOV>
    <SVIZ>63,100000</SVIZ>
    <BSP>63,100000</BSP>
    <MALT>52,000000</MALT>
    <XAUS>63,100000</XAUS>
    <XFRA>63,100000</XFRA>
  </Prezzi>
  <Prezzi>
    <Data>20170107</Data>
    <Mercato>MGP</Mercato>
    <Ora>12</Ora>
    <PUN>59,188070</PUN>
    <NAT>54,000000</NAT>
    <CNOR>65,700000</CNOR>
    <CSUD>48,010000</CSUD>
    <NORD>65,700000</NORD>
    <SARD>48,010000</SARD>
    <SICI>48,010000</SICI>
    <SUD>48,010000</SUD>
    <AUST>65,700000</AUST>
    <BRNN>48,010000</BRNN>
    <COAC>48,010000</COAC>
    <CORS>65,700000</CORS>
    <FOGN>48,010000</FOGN>
    <FRAN>65,700000</FRAN>
    <GREC>48,010000</GREC>
    <MFTV>65,700000</MFTV>
    <PRGP>48,010000</PRGP>
    <ROSN>48,010000</ROSN>
    <SLOV>65,700000</SLOV>
    <SVIZ>65,700000</SVIZ>
    <BSP>65,700000</BSP>
    <MALT>48,010000</MALT>
    <XAUS>65,700000</XAUS>
    <XFRA>65,700000</XFRA>
  </Prezzi>
  <Prezzi>
    <Data>20170107</Data>
    <Mercato>MGP</Mercato>
    <Ora>13</Ora>
    <PUN>51,207350</PUN>
    <NAT>52,180000</NAT>
    <CNOR>55,600000</CNOR>
    <CSUD>43,990000</CSUD>
    <NORD>55,600000</NORD>
    <SARD>43,990000</SARD>
    <SICI>43,990000</SICI>
    <SUD>43,990000</SUD>
    <AUST>55,600000</AUST>
    <BRNN>43,990000</BRNN>
    <COAC>43,990000</COAC>
    <CORS>55,600000</CORS>
    <FOGN>43,990000</FOGN>
    <FRAN>55,600000</FRAN>
    <GREC>43,990000</GREC>
    <MFTV>55,600000</MFTV>
    <PRGP>43,990000</PRGP>
    <ROSN>43,990000</ROSN>
    <SLOV>55,600000</SLOV>
    <SVIZ>55,600000</SVIZ>
    <BSP>55,600000</BSP>
    <MALT>43,990000</MALT>
    <XAUS>55,600000</XAUS>
    <XFRA>55,600000</XFRA>
  </Prezzi>
  <Prezzi>
    <Data>20170107</Data>
    <Mercato>MGP</Mercato>
    <Ora>14</Ora>
    <PUN>53,768210</PUN>
    <NAT>52,190000</NAT>
    <CNOR>49,700000</CNOR>
    <CSUD>43,990000</CSUD>
    <NORD>61,900000</NORD>
    <SARD>43,990000</SARD>
    <SICI>43,990000</SICI>
    <SUD>43,990000</SUD>
    <AUST>61,900000</AUST>
    <BRNN>43,990000</BRNN>
    <COAC>43,990000</COAC>
    <CORS>49,700000</CORS>
    <FOGN>43,990000</FOGN>
    <FRAN>61,900000</FRAN>
    <GREC>43,990000</GREC>
    <MFTV>61,900000</MFTV>
    <PRGP>43,990000</PRGP>
    <ROSN>43,990000</ROSN>
    <SLOV>61,900000</SLOV>
    <SVIZ>61,900000</SVIZ>
    <BSP>61,900000</BSP>
    <MALT>43,990000</MALT>
    <XAUS>61,900000</XAUS>
    <XFRA>61,900000</XFRA>
  </Prezzi>
  <Prezzi>
    <Data>20170107</Data>
    <Mercato>MGP</Mercato>
    <Ora>15</Ora>
    <PUN>52,199680</PUN>
    <NAT>52,190000</NAT>
    <CNOR>53,740000</CNOR>
    <CSUD>49,690000</CSUD>
    <NORD>53,740000</NORD>
    <SARD>49,690000</SARD>
    <SICI>49,690000</SICI>
    <SUD>49,690000</SUD>
    <AUST>53,740000</AUST>
    <BRNN>49,690000</BRNN>
    <COAC>49,690000</COAC>
    <CORS>53,740000</CORS>
    <FOGN>49,690000</FOGN>
    <FRAN>53,740000</FRAN>
    <GREC>49,690000</GREC>
    <MFTV>53,740000</MFTV>
    <PRGP>49,690000</PRGP>
    <ROSN>49,690000</ROSN>
    <SLOV>53,740000</SLOV>
    <SVIZ>53,740000</SVIZ>
    <BSP>53,740000</BSP>
    <MALT>49,690000</MALT>
    <XAUS>53,740000</XAUS>
    <XFRA>53,740000</XFRA>
  </Prezzi>
  <Prezzi>
    <Data>20170107</Data>
    <Mercato>MGP</Mercato>
    <Ora>16</Ora>
    <PUN>53,160380</PUN>
    <NAT>53,000000</NAT>
    <CNOR>53,260000</CNOR>
    <CSUD>53,000000</CSUD>
    <NORD>53,260000</NORD>
    <SARD>53,000000</SARD>
    <SICI>53,000000</SICI>
    <SUD>53,000000</SUD>
    <AUST>53,260000</AUST>
    <BRNN>53,000000</BRNN>
    <COAC>53,000000</COAC>
    <CORS>53,260000</CORS>
    <FOGN>53,000000</FOGN>
    <FRAN>53,260000</FRAN>
    <GREC>53,000000</GREC>
    <MFTV>53,260000</MFTV>
    <PRGP>53,000000</PRGP>
    <ROSN>53,000000</ROSN>
    <SLOV>53,260000</SLOV>
    <SVIZ>53,260000</SVIZ>
    <BSP>53,260000</BSP>
    <MALT>53,000000</MALT>
    <XAUS>53,260000</XAUS>
    <XFRA>53,260000</XFRA>
  </Prezzi>
  <Prezzi>
    <Data>20170107</Data>
    <Mercato>MGP</Mercato>
    <Ora>17</Ora>
    <PUN>58,225020</PUN>
    <NAT>55,240000</NAT>
    <CNOR>59,084140</CNOR>
    <CSUD>59,084140</CSUD>
    <NORD>59,084140</NORD>
    <SARD>59,084140</SARD>
    <SICI>54,000000</SICI>
    <SUD>54,000000</SUD>
    <AUST>59,084140</AUST>
    <BRNN>54,000000</BRNN>
    <COAC>59,084140</COAC>
    <CORS>59,084140</CORS>
    <FOGN>54,000000</FOGN>
    <FRAN>59,084140</FRAN>
    <GREC>54,000000</GREC>
    <MFTV>59,084140</MFTV>
    <PRGP>54,000000</PRGP>
    <ROSN>54,000000</ROSN>
    <SLOV>59,084140</SLOV>
    <SVIZ>59,084140</SVIZ>
    <BSP>59,084140</BSP>
    <MALT>54,000000</MALT>
    <XAUS>59,084140</XAUS>
    <XFRA>59,084140</XFRA>
  </Prezzi>
  <Prezzi>
    <Data>20170107</Data>
    <Mercato>MGP</Mercato>
    <Ora>18</Ora>
    <PUN>68,244400</PUN>
    <NAT>66,230000</NAT>
    <CNOR>69,990390</CNOR>
    <CSUD>69,990390</CSUD>
    <NORD>69,990390</NORD>
    <SARD>69,990390</SARD>
    <SICI>60,000000</SICI>
    <SUD>60,000000</SUD>
    <AUST>69,990390</AUST>
    <BRNN>60,000000</BRNN>
    <COAC>69,990390</COAC>
    <CORS>69,990390</CORS>
    <FOGN>60,000000</FOGN>
    <FRAN>69,990390</FRAN>
    <GREC>60,000000</GREC>
    <MFTV>69,990390</MFTV>
    <PRGP>60,000000</PRGP>
    <ROSN>60,000000</ROSN>
    <SLOV>69,990390</SLOV>
    <SVIZ>69,990390</SVIZ>
    <BSP>69,990390</BSP>
    <MALT>60,000000</MALT>
    <XAUS>69,990390</XAUS>
    <XFRA>69,990390</XFRA>
  </Prezzi>
  <Prezzi>
    <Data>20170107</Data>
    <Mercato>MGP</Mercato>
    <Ora>19</Ora>
    <PUN>75,394250</PUN>
    <NAT>73,500000</NAT>
    <CNOR>76,520000</CNOR>
    <CSUD>76,520000</CSUD>
    <NORD>76,520000</NORD>
    <SARD>76,520000</SARD>
    <SICI>70,000000</SICI>
    <SUD>70,000000</SUD>
    <AUST>76,520000</AUST>
    <BRNN>70,000000</BRNN>
    <COAC>76,520000</COAC>
    <CORS>76,520000</CORS>
    <FOGN>70,000000</FOGN>
    <FRAN>76,520000</FRAN>
    <GREC>70,000000</GREC>
    <MFTV>76,520000</MFTV>
    <PRGP>70,000000</PRGP>
    <ROSN>70,000000</ROSN>
    <SLOV>76,520000</SLOV>
    <SVIZ>76,520000</SVIZ>
    <BSP>76,520000</BSP>
    <MALT>70,000000</MALT>
    <XAUS>76,520000</XAUS>
    <XFRA>76,520000</XFRA>
  </Prezzi>
  <Prezzi>
    <Data>20170107</Data>
    <Mercato>MGP</Mercato>
    <Ora>20</Ora>
    <PUN>78,405720</PUN>
    <NAT>79,000000</NAT>
    <CNOR>78,280000</CNOR>
    <CSUD>78,280000</CSUD>
    <NORD>78,280000</NORD>
    <SARD>78,280000</SARD>
    <SICI>80,000000</SICI>
    <SUD>78,280000</SUD>
    <AUST>78,280000</AUST>
    <BRNN>78,280000</BRNN>
    <COAC>78,280000</COAC>
    <CORS>78,280000</CORS>
    <FOGN>78,280000</FOGN>
    <FRAN>78,280000</FRAN>
    <GREC>78,280000</GREC>
    <MFTV>78,280000</MFTV>
    <PRGP>80,000000</PRGP>
    <ROSN>78,280000</ROSN>
    <SLOV>78,280000</SLOV>
    <SVIZ>78,280000</SVIZ>
    <BSP>78,280000</BSP>
    <MALT>80,000000</MALT>
    <XAUS>78,280000</XAUS>
    <XFRA>78,280000</XFRA>
  </Prezzi>
  <Prezzi>
    <Data>20170107</Data>
    <Mercato>MGP</Mercato>
    <Ora>21</Ora>
    <PUN>68,097190</PUN>
    <NAT>68,000000</NAT>
    <CNOR>68,000000</CNOR>
    <CSUD>68,000000</CSUD>
    <NORD>68,000000</NORD>
    <SARD>68,000000</SARD>
    <SICI>69,290000</SICI>
    <SUD>68,000000</SUD>
    <AUST>68,000000</AUST>
    <BRNN>68,000000</BRNN>
    <COAC>68,000000</COAC>
    <CORS>68,000000</CORS>
    <FOGN>68,000000</FOGN>
    <FRAN>68,000000</FRAN>
    <GREC>68,000000</GREC>
    <MFTV>68,000000</MFTV>
    <PRGP>69,290000</PRGP>
    <ROSN>68,000000</ROSN>
    <SLOV>68,000000</SLOV>
    <SVIZ>68,000000</SVIZ>
    <BSP>68,000000</BSP>
    <MALT>69,290000</MALT>
    <XAUS>68,000000</XAUS>
    <XFRA>68,000000</XFRA>
  </Prezzi>
  <Prezzi>
    <Data>20170107</Data>
    <Mercato>MGP</Mercato>
    <Ora>22</Ora>
    <PUN>59,292260</PUN>
    <NAT>59,520000</NAT>
    <CNOR>60,000000</CNOR>
    <CSUD>60,000000</CSUD>
    <NORD>60,000000</NORD>
    <SARD>60,000000</SARD>
    <SICI>56,000000</SICI>
    <SUD>56,000000</SUD>
    <AUST>60,000000</AUST>
    <BRNN>56,000000</BRNN>
    <COAC>60,000000</COAC>
    <CORS>60,000000</CORS>
    <FOGN>56,000000</FOGN>
    <FRAN>60,000000</FRAN>
    <GREC>56,000000</GREC>
    <MFTV>60,000000</MFTV>
    <PRGP>56,000000</PRGP>
    <ROSN>56,000000</ROSN>
    <SLOV>60,000000</SLOV>
    <SVIZ>60,000000</SVIZ>
    <BSP>60,000000</BSP>
    <MALT>56,000000</MALT>
    <XAUS>60,000000</XAUS>
    <XFRA>60,000000</XFRA>
  </Prezzi>
  <Prezzi>
    <Data>20170107</Data>
    <Mercato>MGP</Mercato>
    <Ora>23</Ora>
    <PUN>59,126620</PUN>
    <NAT>56,000000</NAT>
    <CNOR>60,000000</CNOR>
    <CSUD>60,000000</CSUD>
    <NORD>60,000000</NORD>
    <SARD>60,000000</SARD>
    <SICI>55,000000</SICI>
    <SUD>55,000000</SUD>
    <AUST>60,000000</AUST>
    <BRNN>55,000000</BRNN>
    <COAC>60,000000</COAC>
    <CORS>60,000000</CORS>
    <FOGN>55,000000</FOGN>
    <FRAN>60,000000</FRAN>
    <GREC>55,000000</GREC>
    <MFTV>60,000000</MFTV>
    <PRGP>55,000000</PRGP>
    <ROSN>55,000000</ROSN>
    <SLOV>60,000000</SLOV>
    <SVIZ>60,000000</SVIZ>
    <BSP>60,000000</BSP>
    <MALT>55,000000</MALT>
    <XAUS>60,000000</XAUS>
    <XFRA>60,000000</XFRA>
  </Prezzi>
  <Prezzi>
    <Data>20170107</Data>
    <Mercato>MGP</Mercato>
    <Ora>24</Ora>
    <PUN>57,971290</PUN>
    <NAT>54,000000</NAT>
    <CNOR>52,850000</CNOR>
    <CSUD>52,850000</CSUD>
    <NORD>63,100000</NORD>
    <SARD>52,850000</SARD>
    <SICI>52,850000</SICI>
    <SUD>52,850000</SUD>
    <AUST>63,100000</AUST>
    <BRNN>52,850000</BRNN>
    <COAC>52,850000</COAC>
    <CORS>52,850000</CORS>
    <FOGN>52,850000</FOGN>
    <FRAN>63,100000</FRAN>
    <GREC>52,850000</GREC>
    <MFTV>63,100000</MFTV>
    <PRGP>52,850000</PRGP>
    <ROSN>52,850000</ROSN>
    <SLOV>63,100000</SLOV>
    <SVIZ>63,100000</SVIZ>
    <BSP>63,100000</BSP>
    <MALT>52,850000</MALT>
    <XAUS>63,100000</XAUS>
    <XFRA>63,100000</XFRA>
  </Prezzi>
</NewDataSet>